shavatar/__init__.py
shavatar-1.1.0.dist-info/LICENSE
shavatar-1.1.0.dist-info/WHEEL
shavatar-1.1.0.dist-info/METADATA
shavatar-1.1.0.dist-info/RECORD
